advancedcipher/cipher.py
advancedcipherlib-1.0.0.dist-info/METADATA
advancedcipherlib-1.0.0.dist-info/WHEEL
advancedcipherlib-1.0.0.dist-info/top_level.txt
advancedcipherlib-1.0.0.dist-info/RECORD
